dask_expr/__init__.py
dask_expr/_accessor.py
dask_expr/_backends.py
dask_expr/_categorical.py
dask_expr/_collection.py
dask_expr/_concat.py
dask_expr/_core.py
dask_expr/_cumulative.py
dask_expr/_datetime.py
dask_expr/_describe.py
dask_expr/_dispatch.py
dask_expr/_dummies.py
dask_expr/_expr.py
dask_expr/_groupby.py
dask_expr/_indexing.py
dask_expr/_interchange.py
dask_expr/_merge.py
dask_expr/_merge_asof.py
dask_expr/_quantile.py
dask_expr/_quantiles.py
dask_expr/_reductions.py
dask_expr/_repartition.py
dask_expr/_resample.py
dask_expr/_rolling.py
dask_expr/_shuffle.py
dask_expr/_str_accessor.py
dask_expr/_util.py
dask_expr/_version.py
dask_expr/datasets.py
dask_expr/array/__init__.py
dask_expr/array/_creation.py
dask_expr/array/blockwise.py
dask_expr/array/core.py
dask_expr/array/random.py
dask_expr/array/rechunk.py
dask_expr/array/reductions.py
dask_expr/array/slicing.py
dask_expr/diagnostics/__init__.py
dask_expr/diagnostics/_analyze.py
dask_expr/diagnostics/_analyze_plugin.py
dask_expr/diagnostics/_explain.py
dask_expr/io/__init__.py
dask_expr/io/_delayed.py
dask_expr/io/bag.py
dask_expr/io/csv.py
dask_expr/io/hdf.py
dask_expr/io/io.py
dask_expr/io/json.py
dask_expr/io/orc.py
dask_expr/io/parquet.py
dask_expr/io/records.py
dask_expr/io/sql.py
dask_expr-1.1.20.dist-info/LICENSE.txt
dask_expr-1.1.20.dist-info/METADATA
dask_expr-1.1.20.dist-info/WHEEL
dask_expr-1.1.20.dist-info/top_level.txt
dask_expr-1.1.20.dist-info/RECORD
