Metadata-Version: 2.1
Name: dask-expr
Version: 1.1.20
Summary: High Level Expressions for Dask 
Maintainer-email: Matthew Rocklin <mrocklin@gmail.com>
License: BSD
Project-URL: Source code, https://github.com/dask-contrib/dask-expr/
Keywords: dask pandas
Classifier: Intended Audience :: Developers
Classifier: Intended Audience :: Science/Research
Classifier: License :: OSI Approved :: BSD License
Classifier: Operating System :: OS Independent
Classifier: Programming Language :: Python
Classifier: Programming Language :: Python :: 3
Classifier: Programming Language :: Python :: 3 :: Only
Classifier: Programming Language :: Python :: 3.10
Classifier: Programming Language :: Python :: 3.11
Classifier: Programming Language :: Python :: 3.12
Classifier: Programming Language :: Python :: 3.13
Classifier: Topic :: Scientific/Engineering
Classifier: Topic :: System :: Distributed Computing
Requires-Python: >=3.10
License-File: LICENSE.txt
Requires-Dist: dask==2024.12.0
Requires-Dist: pyarrow>=14.0.1
Requires-Dist: pandas>=2
Provides-Extra: analyze
Requires-Dist: crick; extra == "analyze"
Requires-Dist: distributed; extra == "analyze"
Requires-Dist: graphviz; extra == "analyze"
